pepsickle/__init__.py
pepsickle/__main__.py
pepsickle/model_functions.py
pepsickle/sequence_featurization_tools.py
pepsickle/trained_model_dict.pickle
pepsickle/in-vitro-models/in-vitro_human/model.joblib
pepsickle/in-vitro-models/in-vitro_mammal/model.joblib
pepsickle-0.2.2.dist-info/LICENSE
pepsickle-0.2.2.dist-info/METADATA
pepsickle-0.2.2.dist-info/WHEEL
pepsickle-0.2.2.dist-info/entry_points.txt
pepsickle-0.2.2.dist-info/top_level.txt
pepsickle-0.2.2.dist-info/RECORD
